oma/__init__.py
oma/__main__.py
oma/hl.py
oma/main.py
oma/utils.py
oma-0.1.0.dist-info/entry_points.txt
oma-0.1.0.dist-info/METADATA
oma-0.1.0.dist-info/WHEEL
oma-0.1.0.dist-info/RECORD
